badut/__init__.py
badut/utils/__init__.py
badut/utils/noself.py
badut/utils/requests.py
badut/utils/self.py
badut-0.1.0.dist-info/WHEEL
badut-0.1.0.dist-info/METADATA
badut-0.1.0.dist-info/RECORD
