Metadata-Version: 2.1
Name: badut
Version: 0.1.0
Summary: Python HTTP client designed to be simple in async context
License: MIT
Author: sinkaroid
Author-email: anakmancasan@gmail.com
Requires-Python: >=3.7,<4.0
Classifier: License :: OSI Approved :: MIT License
Classifier: Programming Language :: Python :: 3
Classifier: Programming Language :: Python :: 3.10
Classifier: Programming Language :: Python :: 3.7
Classifier: Programming Language :: Python :: 3.8
Classifier: Programming Language :: Python :: 3.9
